jaxadi/__init__.py
jaxadi/_compile.py
jaxadi/_convert.py
jaxadi/_declare.py
jaxadi/_expand.py
jaxadi/_graph.py
jaxadi/_ops.py
jaxadi/_preprocess.py
jaxadi-0.4.0.dist-info/LICENSE
jaxadi-0.4.0.dist-info/METADATA
jaxadi-0.4.0.dist-info/WHEEL
jaxadi-0.4.0.dist-info/top_level.txt
jaxadi-0.4.0.dist-info/RECORD
