Metadata-Version: 2.2
Name: jaxadi
Version: 0.4.0
Summary: **JaxADi** is a powerful Python library designed to bridge the gap between `casadi.Function` and JAX-compatible functions.
Author-email: Lev Kozlov <l.kozlov@kaist.ac.kr>, Igor Alentev <ialentev@kaist.ac.kr>
Project-URL: homepage, https://github.com/based-robotics/jaxadi
Project-URL: repository, https://github.com/based-robotics/jaxadi.git
Requires-Python: >=3.10
License-File: LICENSE
Requires-Dist: casadi
Requires-Dist: jax
Provides-Extra: dev
Requires-Dist: pre-commit; extra == "dev"
Requires-Dist: pytest; extra == "dev"
